google_datacatalog_connectors_commons_test-0.7.2-py3.7-nspkg.pth
google/datacatalog_connectors/commons_test/__init__.py
google/datacatalog_connectors/commons_test/utils/__init__.py
google/datacatalog_connectors/commons_test/utils/utils.py
google_datacatalog_connectors_commons_test-0.7.2.dist-info/METADATA
google_datacatalog_connectors_commons_test-0.7.2.dist-info/WHEEL
google_datacatalog_connectors_commons_test-0.7.2.dist-info/namespace_packages.txt
google_datacatalog_connectors_commons_test-0.7.2.dist-info/top_level.txt
google_datacatalog_connectors_commons_test-0.7.2.dist-info/RECORD
