Metadata-Version: 2.1
Name: google-datacatalog-connectors-commons-test
Version: 0.7.2
Summary: Common test resources for Data Catalog connectors
Home-page: UNKNOWN
Author: Google LLC
License: UNKNOWN
Platform: Posix; MacOS X; Windows
Classifier: Development Status :: 4 - Beta
Classifier: Intended Audience :: Developers
Classifier: License :: OSI Approved :: Apache Software License
Classifier: Programming Language :: Python
Classifier: Programming Language :: Python :: 2
Classifier: Programming Language :: Python :: 2.7
Classifier: Programming Language :: Python :: 3
Classifier: Programming Language :: Python :: 3.5
Classifier: Programming Language :: Python :: 3.6
Classifier: Programming Language :: Python :: 3.7
Classifier: Operating System :: OS Independent
Classifier: Topic :: Internet
Requires-Dist: pandas (<1.2.0,>=1.1.4)
Requires-Dist: google-datacatalog-connectors-commons (>=0.6.0)
